pywren/__init__.py
pywren/default_config.yaml
pywren/ec2standalone.py
pywren/executor.py
pywren/future.py
pywren/invokers.py
pywren/local.py
pywren/queues.py
pywren/runtime.py
pywren/version.py
pywren/wait.py
pywren/wren.py
pywren/wrenconfig.py
pywren/wrenhandler.py
pywren/wrenlogging.py
pywren/wrenutil.py
pywren/ec2_standalone_files/cloudwatch-agent.config
pywren/ec2_standalone_files/ec2standalone.cloudinit.template
pywren/ec2_standalone_files/supervisord.conf
pywren/ec2_standalone_files/supervisord.init
pywren/jobrunner/jobrunner.py
pywren/scripts/__init__.py
pywren/scripts/pywrencli.py
pywren/scripts/setupscript.py
pywren/scripts/standalone.py
pywren/serialize/__init__.py
pywren/serialize/default_preinstalls.py
pywren/serialize/module_dependency.py
pywren/serialize/serialize.py
pywren/serialize/util.py
pywren/serialize/cloudpickle/__init__.py
pywren/serialize/cloudpickle/cloudpickle.py
pywren/storage/__init__.py
pywren/storage/exceptions.py
pywren/storage/s3_backend.py
pywren/storage/storage.py
pywren/storage/storage_utils.py
pywren-0.4.0.dist-info/METADATA
pywren-0.4.0.dist-info/RECORD
pywren-0.4.0.dist-info/WHEEL
pywren-0.4.0.dist-info/dependency_links.txt
pywren-0.4.0.dist-info/entry_points.txt
pywren-0.4.0.dist-info/top_level.txt
