Metadata-Version: 1.0
Name: pywren
Version: 0.4.0
Summary: Run many jobs transparently on AWS Lambda and other cloud services
Home-page: http://pywren.io
Author: Eric Jonas
Author-email: jonas@ericjonas.com
License: UNKNOWN
Platform: UNKNOWN
